setup.py
rhoPorousMRFPimpleFlux/__init__.py
rhoPorousMRFPimpleFlux.egg-info/PKG-INFO
rhoPorousMRFPimpleFlux.egg-info/SOURCES.txt
rhoPorousMRFPimpleFlux.egg-info/dependency_links.txt
rhoPorousMRFPimpleFlux.egg-info/entry_points.txt
rhoPorousMRFPimpleFlux.egg-info/requires.txt
rhoPorousMRFPimpleFlux.egg-info/top_level.txt
rhoPorousMRFPimpleFlux.egg-info/zip-safe
rhoPorousMRFPimpleFlux/r1_7_1/__init__.py
rhoPorousMRFPimpleFlux/r2_0_0/__init__.py
rhoPorousMRFPimpleFlux/r2_1_0/__init__.py